dorky/__about__.py
dorky/__init__.py
dorky/dorky.py
dorky/search_engines.py
dorky/assets/robots.txt
dorky/assets/images/addon.png
dorky/assets/images/baidu.png
dorky/assets/images/bing.png
dorky/assets/images/brave.png
dorky/assets/images/dorky-addon-popup.png
dorky/assets/images/dorky-head.png
dorky/assets/images/dorky-logo.png
dorky/assets/images/dorky-screenshot.png
dorky/assets/images/duckduckgo.png
dorky/assets/images/favicon.ico
dorky/assets/images/github-mark.png
dorky/assets/images/google.png
dorky/assets/images/yandex.png
dorky/cli/__init__.py
dorky/content/__init__.py
dorky/content/elements.py
dorky/content/help.py
dorky/content/operators.py
dorky/content/popup.py
dorky/json_data/duckduckgo_countries.json
dorky/json_data/search_engines.json
dorky/json_data/yandex_countries.json
dorky_app-0.1.4.dist-info/METADATA
dorky_app-0.1.4.dist-info/WHEEL
dorky_app-0.1.4.dist-info/entry_points.txt
dorky_app-0.1.4.dist-info/licenses/LICENSE
dorky_app-0.1.4.dist-info/RECORD
