Metadata-Version: 2.4
Name: dorky-app
Version: 0.1.4
Summary: Dorky is an OSINT (Open Source Intelligence) tool designed for light to medium-level dorking across multiple search engines.
Project-URL: Homepage, https://github.com/balestek/dorky-app
Project-URL: Bug Tracker, https://github.com/balestek/dorky-app/issues
Author: balestek
License:                     GNU GENERAL PUBLIC LICENSE
License-File: LICENSE
Keywords: bing,brave,dork,dork-conversion,dorking,duckduckgo,google,information-gathering,investigation,open-source-intelligence,osint,osint-python,osint-tool,osint-tools,pipx,pypi,python,search-engine,uv,uvx,yandex
Classifier: Development Status :: 4 - Beta
Classifier: Environment :: Console
Classifier: Environment :: Web Environment
Classifier: Intended Audience :: Education
Classifier: License :: OSI Approved :: GNU General Public License v3 (GPLv3)
Classifier: Natural Language :: English
Classifier: Operating System :: OS Independent
Classifier: Programming Language :: Python :: 3
Classifier: Programming Language :: Python :: 3.8
Classifier: Programming Language :: Python :: 3.9
Classifier: Programming Language :: Python :: 3.10
Classifier: Programming Language :: Python :: 3.11
Classifier: Programming Language :: Python :: 3.12
Classifier: Programming Language :: Python :: 3.13
Requires-Python: >=3.9
Requires-Dist: nicegui==2.24.2
